lilavati/__init__.py
lilavati/Algebra/__init__.py
lilavati/Algebra/addition.py
lilavati/Algebra/combination.py
lilavati/Algebra/cube.py
lilavati/Algebra/cuberoots.py
lilavati/Algebra/permutation.py
lilavati/Algebra/quadraticEqns.py
lilavati/Algebra/sqroot.py
lilavati/Algebra/squares.py
lilavati/Algebra/subtraction.py
lilavati/Algebra/sum_of_permutation.py
lilavati/Algebra/unitConverter.py
lilavati/Geometry/__init__.py
lilavati-1.0.0.dist-info/LICENSE
lilavati-1.0.0.dist-info/METADATA
lilavati-1.0.0.dist-info/WHEEL
lilavati-1.0.0.dist-info/top_level.txt
lilavati-1.0.0.dist-info/RECORD
