Metadata-Version: 2.1
Name: lilavati
Version: 1.0.0
Summary: This library aims at discoving the hidden gems of lilavati, a vedic mathematics book. written by Bhaskaracharya.
Home-page: https://github.com/Project-Leelavati/Leelavati.git
Author: Vedic Pythonist
Author-email: projectleelavati@gmail.com
License: MIT
License-File: LICENSE
